tmo_monitor/__init__.py
tmo_monitor/gateway/arcadyan.py
tmo_monitor/gateway/model.py
tmo_monitor/gateway/nokia.py
tmo_monitor/status.py
tmo_reboot/command_line.py
tmo_reboot-0.2.1.dist-info/LICENSE
tmo_reboot-0.2.1.dist-info/METADATA
tmo_reboot-0.2.1.dist-info/WHEEL
tmo_reboot-0.2.1.dist-info/entry_points.txt
tmo_reboot-0.2.1.dist-info/RECORD
