Metadata-Version: 2.1
Name: tmo-reboot
Version: 0.2.1
Summary: A script to reboot the T-Mobile Home Internet 5G Gateways
Home-page: https://github.com/hugoh/tmo-reboot
License: MIT
Author: Hugo Haas
Author-email: hugoh@hugoh.net
Requires-Python: >=3.8,<4.0
Classifier: License :: OSI Approved :: MIT License
Classifier: Programming Language :: Python :: 3
Classifier: Programming Language :: Python :: 3.8
Classifier: Programming Language :: Python :: 3.9
Classifier: Programming Language :: Python :: 3.10
Classifier: Programming Language :: Python :: 3.11
Classifier: Programming Language :: Python :: 3.12
Requires-Dist: requests (>=2.32.3,<3.0.0)
Project-URL: Repository, https://github.com/hugoh/tmo-reboot
